{
  "anchor": {
    "x": 0.5,
    "y": 1.0
  },
  "assetType": "sprite",
  "blockingPublication": false,
  "characterId": "pata",
  "dimensions": {
    "acceptedExisting": "500x500",
    "preferred": "1024x1024"
  },
  "emotion": "surprised",
  "gaze": "left",
  "layout": null,
  "orientation": null,
  "placeId": null,
  "requestId": "sprite-pata-surprised",
  "requiredFor": [],
  "severity": "catalog-gap",
  "styleReferenceIds": [
    "character-pata-happy-left"
  ],
  "suggestedFilename": "characters/pata/surprised.left.png",
  "transparent": true
}
